ddbg/__init__.py
ddbg/data_influences.py
ddbg/ddbg.py
ddbg/ddbg_results.py
ddbg/proponent_opponent.py
ddbg/self_influence.py
ddbg/trainer.py
ddbg/visualize.py
ddbg/config/__init__.py
ddbg/config/config.py
ddbg/config/defaults.py
ddbg/datasets/__init__.py
ddbg/datasets/cifar10.py
ddbg/datasets/cifar100.py
ddbg/datasets/common.py
ddbg/datasets/fashion_mnist.py
ddbg/datasets/mnist.py
ddbg/demos/ddbg_demo.py
ddbg/models/__init__.py
ddbg/models/base_embed.py
ddbg/models/base_model.py
ddbg/models/embed2.py
ddbg/models/metrics.py
ddbg/models/resnet_preact.py
ddbg/models/toy_cnn.py
ddbg/models/losses/__init__.py
ddbg/models/losses/contrastive.py
ddbg/recipes/cifar10.yaml
ddbg/recipes/cifar10.yaml~
ddbg/recipes/fashion_mnist.yaml
ddbg/recipes/mnist.yaml
ddbg/recipes/mnist.yaml~
ddbg-0.0.2.dist-info/LICENSE
ddbg-0.0.2.dist-info/METADATA
ddbg-0.0.2.dist-info/WHEEL
ddbg-0.0.2.dist-info/top_level.txt
ddbg-0.0.2.dist-info/RECORD
